aws_secrets_env/__init__.py
aws_secrets_env/cli.py
aws_secrets_env/secretsmanager.py
aws_secrets_env-0.1.2.dist-info/METADATA
aws_secrets_env-0.1.2.dist-info/WHEEL
aws_secrets_env-0.1.2.dist-info/entry_points.txt
aws_secrets_env-0.1.2.dist-info/RECORD
